sfdata_stream_parser/__init__.py
sfdata_stream_parser/checks.py
sfdata_stream_parser/collectors.py
sfdata_stream_parser/events.py
sfdata_stream_parser/filters/__init__.py
sfdata_stream_parser/filters/column_headers.py
sfdata_stream_parser/filters/generic.py
sfdata_stream_parser/filters/types.py
sfdata_stream_parser/function_helpers.py
sfdata_stream_parser/functions.py
sfdata_stream_parser/parser/__init__.py
sfdata_stream_parser/parser/csv.py
sfdata_stream_parser/parser/openpyxl.py
sfdata_stream_parser/parser/xml.py
sfdata_stream_parser/stream.py
sfdata_stream_parser/types.py
sfdata_stream_parser-0.6.0.dist-info/LICENSE
sfdata_stream_parser-0.6.0.dist-info/METADATA
sfdata_stream_parser-0.6.0.dist-info/WHEEL
sfdata_stream_parser-0.6.0.dist-info/RECORD
